ocsf_validator/__init__.py
ocsf_validator/__main__.py
ocsf_validator/errors.py
ocsf_validator/matchers.py
ocsf_validator/processor.py
ocsf_validator/reader.py
ocsf_validator/repository.py
ocsf_validator/runner.py
ocsf_validator/type_mapping.py
ocsf_validator/types.py
ocsf_validator/validators.py
ocsf_validator-0.2.3.dist-info/LICENSE
ocsf_validator-0.2.3.dist-info/METADATA
ocsf_validator-0.2.3.dist-info/WHEEL
ocsf_validator-0.2.3.dist-info/RECORD
