Metadata-Version: 2.1
Name: ocsf-validator
Version: 0.2.3
Summary: OCSF Schema Validation
Author: Jeremy Fisher
Author-email: jeremy@query.ai
Requires-Python: >=3.11,<4.0
Classifier: Programming Language :: Python :: 3
Classifier: Programming Language :: Python :: 3.11
Requires-Dist: jsonschema (>=4.21.1,<5.0.0)
Requires-Dist: termcolor (>=2.4.0,<3.0.0)
